consolo/__init__.py
consolo/consolo.py
consolo-0.2.6.dist-info/entry_points.txt
consolo-0.2.6.dist-info/WHEEL
consolo-0.2.6.dist-info/METADATA
consolo-0.2.6.dist-info/licenses/LICENSE
consolo-0.2.6.dist-info/RECORD
