Metadata-Version: 2.1
Name: consolo
Version: 0.2.6
Summary: Utility for pseudo-mounting an AWS lambda filesystem locally
License: MIT
Author-email: Ashton Honnecke <ashton@pixelstub.com>
Requires-Python: >=3.8
Classifier: License :: OSI Approved :: MIT License
Classifier: Operating System :: OS Independent
Classifier: Programming Language :: Python :: 3
Requires-Dist: argdantic>=0.3.0
Requires-Dist: boto3>=1.26.87
Requires-Dist: requests>=2.28.2
Requires-Dist: watchdog>=2.3.1
Project-URL: Bug Tracker, https://github.com/ahonnecke/consolo/issues
Project-URL: Homepage, https://github.com/ahonnecke/consolo
